LICENSE.txt
MANIFEST.in
README.rst
setup.cfg
setup.py
bin/xpy2
bin/xpy3
data/data_file
xpy/Anymethod.py
xpy/Builtins.py
xpy/Clip.py
xpy/Colors.py
xpy/ConsoleImports.py
xpy/Debug.py
xpy/File.py
xpy/History.py
xpy/Main.py
xpy/Micros.py
xpy/ObjectAsDict.py
xpy/Plot.py
xpy/Profiler.py
xpy/RepoHistory.py
xpy/SuperMethod.py
xpy/Text.py
xpy/XPY.py
xpy/__init__.py
xpy/__main__.py
xpy/package_data.dat
xpy.egg-info/PKG-INFO
xpy.egg-info/SOURCES.txt
xpy.egg-info/dependency_links.txt
xpy.egg-info/entry_points.txt
xpy.egg-info/requires.txt
xpy.egg-info/top_level.txt