Metadata-Version: 2.1
Name: xpy
Version: 0.0.11
Summary: It's like Python but now with more "x"
Home-page: https://github.com/dbeal/xpy
Author: David J. Beal
Author-email: david.beal@protonmail.ch
License: MIT
Keywords: xpy
Platform: UNKNOWN
Classifier: Development Status :: 3 - Alpha
Classifier: Intended Audience :: Developers
Classifier: Topic :: Software Development :: Build Tools
Classifier: License :: OSI Approved :: MIT License
Classifier: Programming Language :: Python :: 2
Classifier: Programming Language :: Python :: 2.7
Classifier: Programming Language :: Python :: 3
Classifier: Programming Language :: Python :: 3.3
Classifier: Programming Language :: Python :: 3.4
Classifier: Programming Language :: Python :: 3.5
Provides-Extra: test
Provides-Extra: dev
